mathspell/__init__.py
mathspell/main.py
mathspell/test_main.py
mathspell/helpers/__init__.py
mathspell/helpers/cases.py
mathspell/helpers/constants.py
mathspell/helpers/spacy_tokenizer.py
mathspell-0.1.0.dist-info/METADATA
mathspell-0.1.0.dist-info/WHEEL
mathspell-0.1.0.dist-info/licenses/LICENSE
mathspell-0.1.0.dist-info/RECORD
