Metadata-Version: 2.4
Name: mathspell
Version: 0.1.0
Summary: A library for converting numbers to words contextually.
Project-URL: Documentation, https://github.com/ShaliniR8/mathspell#readme
Project-URL: Issues, https://github.com/ShaliniR8/mathspell/issues
Project-URL: Source, https://github.com/ShaliniR8/mathspell
Author-email: Shalini Roy <shaliniroy1008@gmail.com>
License-Expression: MIT
License-File: LICENSE
Classifier: Programming Language :: Python
Classifier: Programming Language :: Python :: 3.8
Classifier: Programming Language :: Python :: 3.9
Classifier: Programming Language :: Python :: 3.10
Classifier: Programming Language :: Python :: 3.11
Classifier: Programming Language :: Python :: 3.12
Requires-Python: >=3.8
Requires-Dist: num2words
Requires-Dist: spacy
Requires-Dist: unit-parse
